GameBoxUtils/__init__.py
GameBoxUtils/_inputs.py
GameBoxUtils/_vectors.py
gameboxutils-0.2.3.dist-info/METADATA
gameboxutils-0.2.3.dist-info/WHEEL
gameboxutils-0.2.3.dist-info/licenses/LICENSE
gameboxutils-0.2.3.dist-info/RECORD
