Metadata-Version: 2.4
Name: GameBoxUtils
Version: 0.2.3
Summary: A set of helpful code for python
Author-email: Sam Fertig <sfertig007@gmail.com>
License-Expression: MIT
License-File: LICENSE
Classifier: Operating System :: OS Independent
Classifier: Programming Language :: Python :: 3
Requires-Python: >=3.9
